dj_iamport/__init__.py
dj_iamport/choices.py
dj_iamport/client.py
dj_iamport/models/__init__.py
dj_iamport/models/payment.py
dj_iamport/models/payment_cancel.py
dj_iamport-0.0.1.dist-info/LICENSE
dj_iamport-0.0.1.dist-info/METADATA
dj_iamport-0.0.1.dist-info/WHEEL
dj_iamport-0.0.1.dist-info/top_level.txt
dj_iamport-0.0.1.dist-info/RECORD
