Metadata-Version: 2.1
Name: dj-iamport
Version: 0.0.1
Summary: i'mport utility for Django
Author-email: lhy <dev@lhy.kr>
License: MIT License        
Project-URL: GitHub, https://github.com/LeeHanYeong/dj-iamport
Classifier: Framework :: Django
Classifier: Framework :: Django :: 3.2
Classifier: Programming Language :: Python
Classifier: Programming Language :: Python :: 3.9
Requires-Python: >=3.9
License-File: LICENSE
